{
  "version": "7",
  "dialect": "postgresql",
  "entries": [
    {
      "idx": 0,
      "version": "0000",
      "when": 1700000000000,
      "tag": "0000_initial",
      "breakpoints": true
    },
    {
      "idx": 1,
      "version": "0001",
      "when": 1767740900000,
      "tag": "0001_external_stats",
      "breakpoints": true
    },
    {
      "idx": 2,
      "version": "0002",
      "when": 1767752174000,
      "tag": "0002_games_season_type_week",
      "breakpoints": true
    }
  ]
}
